collective.lastlogin-configure.zcml
setup.py
collective/__init__.py
collective.lastlogin.egg-info/PKG-INFO
collective.lastlogin.egg-info/SOURCES.txt
collective.lastlogin.egg-info/dependency_links.txt
collective.lastlogin.egg-info/entry_points.txt
collective.lastlogin.egg-info/namespace_packages.txt
collective.lastlogin.egg-info/not-zip-safe
collective.lastlogin.egg-info/requires.txt
collective.lastlogin.egg-info/top_level.txt
collective/lastlogin/HISTORY.txt
collective/lastlogin/README.txt
collective/lastlogin/__init__.py
collective/lastlogin/configure.zcml
collective/lastlogin/lastlogin.pt
collective/lastlogin/version.txt
collective/lastlogin/view.py
collective/lastlogin/zope2.py