Metadata-Version: 1.0
Name: collective.lastlogin
Version: 0.1
Summary: Show the list of Plone users with the last login date.
Home-page: http://svn.plone.org/svn/collective/collective.lastlogin
Author: Zest Software
Author-email: info@zestsoftware.nl
License: GPL
Platform: UNKNOWN
Classifier: Framework :: Plone
Classifier: Programming Language :: Python
